wavsetpos/__init__.py
wavsetpos-1.1.dist-info/LICENSE.txt
wavsetpos-1.1.dist-info/METADATA
wavsetpos-1.1.dist-info/WHEEL
wavsetpos-1.1.dist-info/top_level.txt
wavsetpos-1.1.dist-info/RECORD
