Metadata-Version: 2.1
Name: wavsetpos
Version: 1.1
Summary: A library for setting pos of a wav file with pygame.mixer.music
Home-page: 
Author: Raymond Grottodden
Author-email: raymondgrotto651@gmail.com
License: MIT
Keywords: pygame,wav,music,mixer
Classifier: Development Status :: 5 - Production/Stable
Classifier: Intended Audience :: Education
Classifier: Operating System :: Microsoft :: Windows :: Windows 10
Classifier: License :: OSI Approved :: MIT License
Classifier: Programming Language :: Python :: 3
License-File: LICENSE.txt
Requires-Dist: pydub ==0.25.1
